flask_azure_oauth/__init__.py
flask_azure_oauth/errors.py
flask_azure_oauth/mocks/__init__.py
flask_azure_oauth/mocks/keys.py
flask_azure_oauth/mocks/tokens.py
flask_azure_oauth/resource_protector.py
flask_azure_oauth/tokens.py
flask_azure_oauth-0.6.0.dist-info/LICENSE.md
flask_azure_oauth-0.6.0.dist-info/WHEEL
flask_azure_oauth-0.6.0.dist-info/METADATA
flask_azure_oauth-0.6.0.dist-info/RECORD
