Metadata-Version: 2.1
Name: flask-azure-oauth
Version: 0.6.0
Summary: Python Flask extension for using Azure Active Directory with OAuth to protect applications
Home-page: https://github.com/antarctica/flask-azure-oauth
License: MIT
Author: Felix Fennell
Author-email: felnne@bas.ac.uk
Requires-Python: >=3.6,<4.0
Classifier: Development Status :: 5 - Production/Stable
Classifier: Framework :: Flask
Classifier: Intended Audience :: Developers
Classifier: License :: OSI Approved :: MIT License
Classifier: License :: Other/Proprietary License
Classifier: Operating System :: OS Independent
Classifier: Programming Language :: Python :: 3
Classifier: Programming Language :: Python :: 3.10
Classifier: Programming Language :: Python :: 3.6
Classifier: Programming Language :: Python :: 3.7
Classifier: Programming Language :: Python :: 3.8
Classifier: Programming Language :: Python :: 3.9
Requires-Dist: Flask (>=2.0.2,<3.0.0)
Requires-Dist: authlib (==0.14.3)
Requires-Dist: requests (>=2.23.0,<3.0.0)
Project-URL: Repository, https://github.com/antarctica/flask-azure-oauth
